touca/__init__.py
touca/_case.py
touca/_client.py
touca/_options.py
touca/_printer.py
touca/_rules.py
touca/_runner.py
touca/_transport.py
touca/_types.py
touca/_utils.py
touca/cli/__init__.py
touca/cli/__main__.py
touca/cli/check.py
touca/cli/common.py
touca/cli/config.py
touca/cli/execute.py
touca/cli/help.py
touca/cli/login.py
touca/cli/plugin.py
touca/cli/plugins/demo.py
touca/cli/profile.py
touca/cli/profiles/install.sh
touca/cli/profiles/profile.schema.json
touca/cli/profiles/sample.json
touca/cli/results/__init__.py
touca/cli/results/common.py
touca/cli/results/compress.py
touca/cli/results/edit.py
touca/cli/results/extract.py
touca/cli/results/list.py
touca/cli/results/merge.py
touca/cli/results/post.py
touca/cli/results/remove.py
touca/cli/run.py
touca/cli/server.py
touca/plugins/django.py
touca/py.typed
touca-1.8.7.dist-info/entry_points.txt
touca-1.8.7.dist-info/LICENSE
touca-1.8.7.dist-info/WHEEL
touca-1.8.7.dist-info/METADATA
touca-1.8.7.dist-info/RECORD
