Metadata-Version: 2.1
Name: touca
Version: 1.8.7
Summary: Touca SDK for Python
Home-page: https://touca.io
License: Apache-2.0
Keywords: touca,snapshot testing,regression testing
Author: Touca, Inc.
Author-email: hello@touca.io
Maintainer: Pejman Ghorbanzade
Maintainer-email: pejman@touca.io
Requires-Python: >=3.7,<4.0
Classifier: Development Status :: 4 - Beta
Classifier: Intended Audience :: Developers
Classifier: License :: OSI Approved :: Apache Software License
Classifier: Natural Language :: English
Classifier: Operating System :: OS Independent
Classifier: Programming Language :: Python
Classifier: Programming Language :: Python :: 3
Classifier: Programming Language :: Python :: 3.7
Classifier: Programming Language :: Python :: 3.8
Classifier: Programming Language :: Python :: 3.9
Classifier: Programming Language :: Python :: 3.10
Classifier: Programming Language :: Python :: 3.11
Classifier: Programming Language :: Python :: 3
Classifier: Programming Language :: Python :: 3 :: Only
Classifier: Programming Language :: Python :: 3.10
Classifier: Programming Language :: Python :: 3.11
Classifier: Programming Language :: Python :: 3.7
Classifier: Programming Language :: Python :: 3.8
Classifier: Programming Language :: Python :: 3.9
Requires-Dist: certifi (>=2022.12.7,<2023.0.0)
Requires-Dist: flatbuffers (>=23.1.4,<24.0.0)
Requires-Dist: rich (>=12.6.0,<13.0.0)
Requires-Dist: touca-fbs (>=0.0.3,<0.0.4)
Requires-Dist: urllib3 (>=1.26.14,<2.0.0)
Project-URL: Changelog, https://github.com/trytouca/trytouca/blob/main/sdk/python/Changelog.md
Project-URL: Documentation, https://touca.io/docs
Project-URL: Repository, https://github.com/trytouca/trytouca
Project-URL: Twitter, https://twitter.com/trytouca
